LICENSE
MANIFEST.in
README
README.md
setup.py
html_purifier3.egg-info/PKG-INFO
html_purifier3.egg-info/SOURCES.txt
html_purifier3.egg-info/dependency_links.txt
html_purifier3.egg-info/top_level.txt
purifier/__init__.py
purifier/forms.py
purifier/models.py
purifier/purifier.py
purifier/test.py
purifier/whitelist.py
test-data/custom-1.html
test-data/google.ru.html
test-data/megatyumen.ru.catalogue.html
test-data/megatyumen.ru.html
test-data/quoted_test.html
test-data/simple.html