Metadata-Version: 1.1
Name: html-purifier3
Version: 2.1.0
Summary: Cuts the tags and attributes from HTML that are not in the
Home-page: https://github.com/meunierd/python-html-purifier
Author: meunierd
Author-email: devon@eventmobi.com
License: GPL3
Platform: UNKNOWN
Classifier: Operating System :: OS Independent
Classifier: Programming Language :: Python
